python_zillow-0.2.0.dist-info/DESCRIPTION.rst
python_zillow-0.2.0.dist-info/LICENSE.txt
python_zillow-0.2.0.dist-info/METADATA
python_zillow-0.2.0.dist-info/RECORD
python_zillow-0.2.0.dist-info/WHEEL
python_zillow-0.2.0.dist-info/metadata.json
python_zillow-0.2.0.dist-info/top_level.txt
zillow/__init__.py
zillow/api.py
zillow/error.py
zillow/place.py
